docxtpl/__init__.py
docxtpl/__main__.py
docxtpl/inline_image.py
docxtpl/listing.py
docxtpl/richtext.py
docxtpl/subdoc.py
docxtpl/template.py
docxtpl-0.20.1.dist-info/METADATA
docxtpl-0.20.1.dist-info/WHEEL
docxtpl-0.20.1.dist-info/eager_resources.txt
docxtpl-0.20.1.dist-info/top_level.txt
docxtpl-0.20.1.dist-info/RECORD
