Metadata-Version: 2.1
Name: docxtpl
Version: 0.20.1
Summary: Python docx template engine
Home-page: https://github.com/elapouya/python-docx-template
Author: Eric Lapouyade
License: LGPL-2.1-only
Keywords: jinja2
Classifier: Intended Audience :: Developers
Classifier: Development Status :: 4 - Beta
Classifier: Programming Language :: Python :: 3
Classifier: Programming Language :: Python :: 3.7
Classifier: Programming Language :: Python :: 3.8
Classifier: Programming Language :: Python :: 3.9
Classifier: Programming Language :: Python :: 3.10
Classifier: Programming Language :: Python :: 3.11
Classifier: Programming Language :: Python :: 3.12
Requires-Dist: python-docx>=1.1.1
Requires-Dist: docxcompose
Requires-Dist: jinja2
Requires-Dist: lxml
Provides-Extra: docs
Requires-Dist: Sphinx; extra == "docs"
Requires-Dist: sphinxcontrib-napoleon; extra == "docs"
